LICENSE
README.md
setup.py
stac_cat_utils/__init__.py
stac_cat_utils/stac.py
stac_cat_utils/stac_generator.py
stac_cat_utils/utils.py
stac_cat_utils.egg-info/PKG-INFO
stac_cat_utils.egg-info/SOURCES.txt
stac_cat_utils.egg-info/dependency_links.txt
stac_cat_utils.egg-info/requires.txt
stac_cat_utils.egg-info/top_level.txt
stac_cat_utils/slc/__init__.py
stac_cat_utils/slc/bands.py
stac_cat_utils/slc/commands.py
stac_cat_utils/slc/constants.py
stac_cat_utils/slc/metadata_links.py
stac_cat_utils/slc/product_metadata.py
stac_cat_utils/slc/properties.py
stac_cat_utils/slc/stac.py
test/test_stac_generator.py