Metadata-Version: 2.1
Name: stac-cat-utils
Version: 0.1.0
Summary: Package of utility functions facilitating generation of STAC files from existing files and folders.
Home-page: https://github.com/SpaceApplications/stac-cat-utils
Author: Space Applications Services
Author-email: sys_eos@spaceapplications.com
License: BSD
Keywords: STAC,pystac,STAC generation
Requires-Python: >=3.8
License-File: LICENSE
